Products.LDAPMultiPlugins-5.1-py3.11-nspkg.pth
Products/LDAPMultiPlugins/ActiveDirectoryMultiPlugin.py
Products/LDAPMultiPlugins/LDAPMultiPlugin.py
Products/LDAPMultiPlugins/LDAPPluginBase.py
Products/LDAPMultiPlugins/__init__.py
Products/LDAPMultiPlugins/configure.zcml
Products/LDAPMultiPlugins/exportimport.py
Products/LDAPMultiPlugins/interfaces.py
Products/LDAPMultiPlugins/dtml/addActiveDirectoryMultiPlugin.dtml
Products/LDAPMultiPlugins/dtml/addLDAPMultiPlugin.dtml
Products/LDAPMultiPlugins/tests/__init__.py
Products/LDAPMultiPlugins/tests/base.py
Products/LDAPMultiPlugins/tests/test_LDAPMultiPlugins.py
Products/LDAPMultiPlugins/tests/test_exportimport.py
Products.LDAPMultiPlugins-5.1.dist-info/LICENSE.txt
Products.LDAPMultiPlugins-5.1.dist-info/METADATA
Products.LDAPMultiPlugins-5.1.dist-info/WHEEL
Products.LDAPMultiPlugins-5.1.dist-info/entry_points.txt
Products.LDAPMultiPlugins-5.1.dist-info/namespace_packages.txt
Products.LDAPMultiPlugins-5.1.dist-info/top_level.txt
Products.LDAPMultiPlugins-5.1.dist-info/RECORD
