Metadata-Version: 2.1
Name: Products.LDAPMultiPlugins
Version: 5.1
Summary: LDAP-backed plugins for the Zope PluggableAuthService
Home-page: https://github.com/dataflake/Products.LDAPMultiPlugins
Author: Jens Vagelpohl and contributors
Author-email: jens@dataflake.org
License: ZPL 2.1
Project-URL: Documentation, https://productsldapmultiplugins.readthedocs.io/
Project-URL: Issue Tracker, https://github.com/dataflake/Products.LDAPMultiPlugins/issues
Project-URL: Sources, https://github.com/dataflake/Products.LDAPMultiPlugins
Keywords: web application server zope ldap
Classifier: Development Status :: 6 - Mature
Classifier: Framework :: Zope
Classifier: Framework :: Zope :: 5
Classifier: Intended Audience :: Developers
Classifier: License :: OSI Approved :: Zope Public License
Classifier: Operating System :: OS Independent
Classifier: Programming Language :: Python :: 3
Classifier: Programming Language :: Python :: 3.7
Classifier: Programming Language :: Python :: 3.8
Classifier: Programming Language :: Python :: 3.9
Classifier: Programming Language :: Python :: 3.10
Classifier: Programming Language :: Python :: 3.11
Classifier: Programming Language :: Python :: 3.12
Classifier: Topic :: Internet :: WWW/HTTP :: Site Management
Classifier: Topic :: Software Development
Classifier: Topic :: System :: Systems Administration :: Authentication/Directory :: LDAP
Requires-Python: >=3.7
License-File: LICENSE.txt
Requires-Dist: setuptools
Requires-Dist: Zope >=5
Requires-Dist: Products.LDAPUserFolder
Requires-Dist: Products.PluggableAuthService
Provides-Extra: docs
Requires-Dist: Sphinx ; extra == 'docs'
Requires-Dist: sphinx-rtd-theme ; extra == 'docs'
Requires-Dist: repoze.sphinx.autointerface ; extra == 'docs'
Requires-Dist: pkginfo ; extra == 'docs'
Provides-Extra: exportimport
Requires-Dist: Products.GenericSetup >=2.0b1 ; extra == 'exportimport'
